fastmcp_time_service/__init__.py
fastmcp_time_service/server.py
fastmcp_time_service-1.2.0.dist-info/licenses/LICENSE
fastmcp_time_service-1.2.0.dist-info/METADATA
fastmcp_time_service-1.2.0.dist-info/WHEEL
fastmcp_time_service-1.2.0.dist-info/entry_points.txt
fastmcp_time_service-1.2.0.dist-info/top_level.txt
fastmcp_time_service-1.2.0.dist-info/RECORD
