Metadata-Version: 2.4
Name: fastmcp-time-service
Version: 1.2.0
Summary: 基于SSE传输的MCP时间服务器，提供多时区时间查询功能
Author-email: AlexLIAOwang <liaowang@example.com>
License: MIT
Project-URL: Homepage, https://github.com/AlexLIAOwang/fastmcp-time-service
Project-URL: Repository, https://github.com/AlexLIAOwang/fastmcp-time-service
Project-URL: Documentation, https://github.com/AlexLIAOwang/fastmcp-time-service/blob/main/README.md
Project-URL: Issues, https://github.com/AlexLIAOwang/fastmcp-time-service/issues
Keywords: mcp,time,timezone,fastmcp,model-context-protocol
Classifier: Development Status :: 4 - Beta
Classifier: Intended Audience :: Developers
Classifier: License :: OSI Approved :: MIT License
Classifier: Programming Language :: Python :: 3
Classifier: Programming Language :: Python :: 3.8
Classifier: Programming Language :: Python :: 3.9
Classifier: Programming Language :: Python :: 3.10
Classifier: Programming Language :: Python :: 3.11
Classifier: Programming Language :: Python :: 3.12
Classifier: Topic :: Software Development :: Libraries :: Python Modules
Classifier: Topic :: Internet :: WWW/HTTP :: Dynamic Content
Classifier: Topic :: System :: Networking :: Time Synchronization
Requires-Python: >=3.8
License-File: LICENSE
Requires-Dist: mcp>=1.6.0
Requires-Dist: pytz>=2024.1
Requires-Dist: python-dotenv>=1.0.0
Provides-Extra: dev
Requires-Dist: pytest>=7.0.0; extra == "dev"
Requires-Dist: pytest-asyncio>=0.21.0; extra == "dev"
Requires-Dist: black>=23.0.0; extra == "dev"
Requires-Dist: ruff>=0.1.0; extra == "dev"
Dynamic: license-file
